generated/Karatsuba.v
module Karatsuba(
  input         clock,
  input         reset,
  input  [31:0] io_a,
  input  [31:0] io_b,
  output [63:0] io_out
);
`ifdef RANDOMIZE_REG_INIT
  reg [63:0] _RAND_0;
`endif // RANDOMIZE_REG_INIT
  reg [63:0] C; // @[Karatsuba.scala 14:18]
  wire [31:0] _T0_T_2 = io_a[15:0] * io_b[15:0]; // @[Karatsuba.scala 16:20]
  wire [15:0] _T1_T_3 = io_a[31:16] + io_a[15:0]; // @[Karatsuba.scala 17:22]
  wire [15:0] _T1_T_7 = io_b[31:16] + io_b[15:0]; // @[Karatsuba.scala 17:47]
  wire [31:0] _T1_T_8 = _T1_T_3 * _T1_T_7; // @[Karatsuba.scala 17:34]
  wire [31:0] _T2_T_2 = io_a[31:16] * io_b[31:16]; // @[Karatsuba.scala 18:21]
  wire [63:0] T2 = {{32'd0}, _T2_T_2};
  wire [95:0] _C_T = {T2,32'h0}; // @[Cat.scala 31:58]
  wire [63:0] T1 = {{32'd0}, _T1_T_8};
  wire [63:0] T0 = {{32'd0}, _T0_T_2};
  wire [63:0] _C_T_2 = T1 - T0; // @[Karatsuba.scala 20:34]
  wire [63:0] _C_T_4 = _C_T_2 - T2; // @[Karatsuba.scala 20:37]
  wire [79:0] _C_T_5 = {_C_T_4,16'h0}; // @[Cat.scala 31:58]
  wire [95:0] _GEN_0 = {{16'd0}, _C_T_5}; // @[Karatsuba.scala 20:26]
  wire [95:0] _C_T_7 = _C_T + _GEN_0; // @[Karatsuba.scala 20:26]
  wire [95:0] _GEN_1 = {{32'd0}, T0}; // @[Karatsuba.scala 20:52]
  wire [95:0] _C_T_9 = _C_T_7 + _GEN_1; // @[Karatsuba.scala 20:52]
  wire [95:0] _GEN_2 = reset ? 96'h0 : _C_T_9; // @[Karatsuba.scala 14:{18,18} 20:6]
  assign io_out = C; // @[Karatsuba.scala 21:11]
  always @(posedge clock) begin
    C <= _GEN_2[63:0]; // @[Karatsuba.scala 14:{18,18} 20:6]
  end
// Register and memory initialization
`ifdef RANDOMIZE_GARBAGE_ASSIGN
`define RANDOMIZE
`endif
`ifdef RANDOMIZE_INVALID_ASSIGN
`define RANDOMIZE
`endif
`ifdef RANDOMIZE_REG_INIT
`define RANDOMIZE
`endif
`ifdef RANDOMIZE_MEM_INIT
`define RANDOMIZE
`endif
`ifndef RANDOM
`define RANDOM $random
`endif
`ifdef RANDOMIZE_MEM_INIT
  integer initvar;
`endif
`ifndef SYNTHESIS
`ifdef FIRRTL_BEFORE_INITIAL
`FIRRTL_BEFORE_INITIAL
`endif
initial begin
  `ifdef RANDOMIZE
    `ifdef INIT_RANDOM
      `INIT_RANDOM
    `endif
    `ifndef VERILATOR
      `ifdef RANDOMIZE_DELAY
        #`RANDOMIZE_DELAY begin end
      `else
        #0.002 begin end
      `endif
    `endif
`ifdef RANDOMIZE_REG_INIT
  _RAND_0 = {2{`RANDOM}};
  C = _RAND_0[63:0];
`endif // RANDOMIZE_REG_INIT
  `endif // RANDOMIZE
end // initial
`ifdef FIRRTL_AFTER_INITIAL
`FIRRTL_AFTER_INITIAL
`endif
`endif // SYNTHESIS
endmodule

test_run_dir/Karatsuba_should_pass/Karatsuba.vcd
$date
2023-11-29T08:59+0000
$end
$version
0.2
$end
$comment

$end
$timescale 1ns  $end
$scope module Karatsuba $end
 $var wire 64 ! io_out $end
 $var wire 64 " T0 $end
 $var wire 64 # T2 $end
 $var wire 64 $ C $end
 $var wire 32 % io_b $end
 $var wire 1 & clock $end
 $var wire 64 ' T1 $end
 $var wire 32 ( io_a $end
 $var wire 1 ) reset $end
$upscope $end
$enddefinitions $end
$dumpvars
0)
b0000000000000000000000000000000000000000000000000000000000000000 "
0&
b0000000000000000000000000000000000000000000000000000000000000000 #
b00000000000000000000000000000000 (
b0000000000000000000000000000000000000000000000000000000000000000 '
b0000000000000000000000000000000000000000000000000000000000000000 $
b0000000000000000000000000000000000000000000000000000000000000000 !
b00000000000000000000000000000000 %
$end
#0
1)
#1
1&
#6
b11010000010000000000000010001001 %
b0000000000000000000000000000000000000000000000111100010001011010 "
0&
b0000000000000000000000000000000000000000001001010110101110000000 #
b0000000000000000000000000000000000000101111000110010101011111000 '
b00000000001011100000011100001010 (
0)
#11
b0000000000100101011100010011100111111011001000011100010001011010 !
1&
b0000000000100101011100010011100111111011001000011100010001011010 $
#16
b11100000101100000000000011011100 %
b0000000000000000000000000000000000000000000000110111000011011100 "
0&
b0000000000000000000000000000000000000000011011001101010101000000 #
b0000000000000000000000000000000000000011111101000101000101011100 '
b00000000011111000000010000000001 (
#21
b0000000001101100110110001100010000001011010000110111000011011100 !
1&
b0000000001101100110110001100010000001011010000110111000011011100 $
#26
b10110000010100000000000011110100 %
b0000000000000000000000000000000000000000000001011011110011000100 "
0&
b0000000000000000000000000000000000001011010101001110010001000000 #
b0000000000000000000000000000000000001111100011111010000100100100 '
b00010000011101000000011000000101 (
#31
b0000101101010100111010000111010100000000001001011011110011000100 !
1&
b0000101101010100111010000111010100000000001001011011110011000100 $
#36
b11010000000100000000000000011010 %
b0000000000000000000000000000000000000000000000000001101000110100 "
0&
b0000000000000000000000000000000001110101110011011010111100100000 #
b0000000000000000000000000000000001110110101011100011001000001000 '
b10010000111100100000000100000010 (
#41
b0111010111001101101100000000000001101000101101000001101000110100 !
1&
b0111010111001101101100000000000001101000101101000001101000110100 $
#46
b01010000110100000000000010000100 %
b0000000000000000000000000000000000000000000001101011011110011100 "
0&
b0000000000000000000000000000000000101101110001010111111100110000 #
b0000000000000000000000000000000000110010001100111011111111111000 '
b10010000111111110000110100000111 (
#51
b0010110111000101100000111001011110001001001100101011011110011100 !
1&
b0010110111000101100000111001011110001001001100101011011110011100 $
#56
b00000000110100000000000011010001 %
b0000000000000000000000000000000000000000000000100111001111010001 "
0&
b0000000000000000000000000000000000000000110000110000000110100000 #
b0000000000000000000000000000000000000001100010111101011111100011 '
b11110000000000100000001100000001 (
#61
b0000000011000011000000100110011001100010011101000111001111010001 !
1&
b0000000011000011000000100110011001100010011101000111001111010001 $
#66
b00000000001000000000000011000110 %
b0000000000000000000000000000000000000000000001010111010110011010 "
0&
b0000000000000000000000000000000000000000000011100000111010000000 #
b0000000000000000000000000000000000000000011010110101111110110010 '
b01110000011101000000011100001111 (
#71
b0000000000001110000011101101011111011011100111010111010110011010 !
1&
b0000000000001110000011101101011111011011100111010111010110011010 $
#76
b00110000100100000000000010100111 %
b0000000000000000000000000000000000000000000000010101001100111000 "
0&
b0000000000000000000000000000000000001100001100001000010100100000 #
b0000000000000000000000000000000000001100101111100110011111100110 '
b01000000010000100000001000001000 (
#81
b0000110000110000100001011010110010001111100011110101001100111000 !
1&
b0000110000110000100001011010110010001111100011110101001100111000 $
#86
b01000000101100000000000001111010 %
b0000000000000000000000000000000000000000000000111101010011000100 "
0&
b0000000000000000000000000000000000000100000011010000010110000000 #
b0000000000000000000000000000000000000110001000001000010011110100 '
b00010000000010000000100000001010 (
#91
b0000010000001101000001111000111110101010101100111101010011000100 !
1&
b0000010000001101000001111000111110101010101100111101010011000100 $
#96
b01110000111100000000000001000101 %
b0000000000000000000000000000000000000000000000001101001010000001 "
0&
b0000000000000000000000000000000001100010111110000110000110010000 #
b0000000000000000000000000000000001100100100011100011011110110100 '
b11100000010101110000001100001101 (
#101
b0110001011111000011000110010010100000011101000111101001010000001 !
1&
b0110001011111000011000110010010100000011101000111101001010000001 $
#106
b00010000001100000000000010011011 %
b0000000000000000000000000000000000000000000000001001101110011011 "
0&
b0000000000000000000000000000000000000100000100011111000110100000 #
b0000000000000000000000000000000000000100010010011100011001010101 '
b01000000010111100000000100000001 (
#111
b0000010000010001111100011101011100111001000110101001101110011011 !
1&
b0000010000010001111100011101011100111001000110101001101110011011 $
#116
b10000000011000000000000001010111 %
b0000000000000000000000000000000000000000000000000000000100000101 "
0&
b0000000000000000000000000000000000010000100010010101110111000000 #
b0000000000000000000000000000000000010000100101100001010011011011 '
b00100000111110100000000000000011 (
#121
b0001000010001001010111011100110010110110000101100000000100000101 !
1&
b0001000010001001010111011100110010110110000101100000000100000101 $
#126
b01010000100000000000000011011011 %
b0000000000000000000000000000000000000000000000011011111010001110 "
0&
b0000000000000000000000000000000000101000011001011011110000000000 #
b0000000000000000000000000000000000101001011110011000011000110110 '
b10000000011110000000001000001010 (
#131
b0010100001100101101111010001001000001011101010011011111010001110 !
1&
b0010100001100101101111010001001000001011101010011011111010001110 $
#136
b10110000101100000000000001111111 %
b0000000000000000000000000000000000000000000000101111110011111010 "
0&
b0000000000000000000000000000000010011010111011001101001010000000 #
b0000000000000000000000000000000010011111100001110110111100100010 '
b11100000011110000000011000000110 (
#141
b1001101011101100110101110001011110011111101010101111110011111010 !
1&
b1001101011101100110101110001011110011111101010101111110011111010 $
#146
b10110000100100000000000000001101 %
b0000000000000000000000000000000000000000000000000000110101110101 "
0&
b0000000000000000000000000000000000000000100011110111010100000000 #
b0000000000000000000000000000000000000001010001100101001000010101 '
b00000000110100000000000100001001 (
#151
b0000000010001111011101011011011011001111101000000000110101110101 !
1&
b0000000010001111011101011011011011001111101000000000110101110101 $
#156
b10010000111100000000000001111011 %
b0000000000000000000000000000000000000000000000011111001010111010 "
0&
b0000000000000000000000000000000001100011101100101001011010000000 #
b0000000000000000000000000000000001100110010101001101000111100010 '
b10110000000110000000010000001110 (
#161
b0110001110110010100110010010000001001000101010011111001010111010 !
1&
b0110001110110010100110010010000001001000101010011111001010111010 $
#166
b11110000111100000000000000100111 %
b0000000000000000000000000000000000000000000000011101010111010100 "
0&
b0000000000000000000000000000000000111100010001110100101101000000 #
b0000000000000000000000000000000001000111101010010110111000101000 '
b01000000000011000000110000001100 (
#171
b0011110001000111010101101010000001001101000101011101010111010100 !
1&
b0011110001000111010101101010000001001101000101011101010111010100 $
#176
b10110000011100000000000000001001 %
b0000000000000000000000000000000000000000000000000000100101100011 "
0&
b0000000000000000000000000000000001100011100000101000101011100000 #
b0000000000000000000000000000000001100100001111111010110010000101 '
b10010000011000100000000100001011 (
#181
b0110001110000010100010111001110100011000010000100000100101100011 !
1&
b0110001110000010100010111001110100011000010000100000100101100011 $
#186
b10100000001100000000000010110000 %
b0000000000000000000000000000000000000000000001111001010110000000 "
0&
b0000000000000000000000000000000001111000001111000110011101010000 #
b0000000000000000000000000000000001111111101011110010100100100000 '
b11000000001001110000101100001000 (
#191
b0111100000111100011011101011101100101100010101111001010110000000 !
1&
b0111100000111100011011101011101100101100010101111001010110000000 $
#196
b00000000101100000000000001001100 %
b0000000000000000000000000000000000000000000000110100100001110100 "
0&
b0000000000000000000000000000000000000000010011011001010010000000 #
b0000000000000000000000000000000000000000011110011111011101100100 '
b01110000110110000000101100001111 (
#201
b0000000001001101100101001010100100011010011100110100100001110100 !
1&
b0000000001001101100101001010100100011010011100110100100001110100 $
#206
b00010000011100000000000011011000 %
b0000000000000000000000000000000000000000000001111001100000000000 "
0&
b0000000000000000000000000000000000001101011000000110010011000000 #
b0000000000000000000000000000000000001110101010111011001110100000 '
b11010000010101000000100100000000 (
#211
b0000110101100000011001100000001110110110111001111001100000000000 !
1&
b0000110101100000011001100000001110110110111001111001100000000000 $
#216
b01100000000100000000000011000110 %
b0000000000000000000000000000000000000000000010111010000110111100 "
0&
b0000000000000000000000000000000001001000010010110110101010010000 #
b0000000000000000000000000000000001001110100100001011111110100010 '
b11000000101010010000111100001010 (
#221
b0100100001001011011100001100100110110011011000011010000110111100 !
1&
b0100100001001011011100001100100110110011011000011010000110111100 $
#226
b00100000000100000000000010010111 %
b0000000000000000000000000000000000000000000000100110000101001111 "
0&
b0000000000000000000000000000000000010000000111101100101101100000 #
b0000000000000000000000000000000000010000111011100111100010011001 '
b10000000101101100000010000001001 (
#231
b0001000000011110110011000010110101001011111011000110000101001111 !
1&
b0001000000011110110011000010110101001011111011000110000101001111 $
#236
b11010000000100000000000000011111 %
b0000000000000000000000000000000000000000000000010101010101011101 "
0&
b0000000000000000000000000000000001001110001001000001001001010000 #
b0000000000000000000000000000000001010111001001000010110001011000 '
b01100000001001010000101100000011 (
#241
b0100111000100100000110110100111011000100101011000101010101011101 !
1&
b0100111000100100000110110100111011000100101011000101010101011101 $
#246
b00100000001000000000000001111111 %
b0000000000000000000000000000000000000000000000111111110011110110 "
0&
b0000000000000000000000000000000000011100001001101110101011100000 #
b0000000000000000000000000000000000011101100111000111010000111111 '
b11100000010101110000100000001010 (
#251
b0001110000100110111011000101000110001100011011001111110011110110 !
1&
b0001110000100110111011000101000110001100011011001111110011110110 $
#256
b01100000001000000000000001001010 %
b0000000000000000000000000000000000000000000000110011000010011010 "
0&
b0000000000000000000000000000000001000010000110111010000111100000 #
b0000000000000000000000000000000001000110011101100111011111110000 '
b10110000000011110000101100001001 (
#261
b0100001000011011101001100011011110100101011110010011000010011010 !
1&
b0100001000011011101001100011011110100101011110010011000010011010 $
#266
b01100000111000000000000000011101 %
b0000000000000000000000000000000000000000000000001001000100011101 "
0&
b0000000000000000000000000000000000110000011110000101001101000000 #
b0000000000000000000000000000000000110010011011000010011110111011 '
b10000000000101100000010100000001 (
#271
b0011000001111000010101010011001101000011010111101001000100011101 !
1&
b0011000001111000010101010011001101000011010111101001000100011101 $
#276
b01010000011100000000000011010110 %
b0000000000000000000000000000000000000000000000001110000011011110 "
0&
b0000000000000000000000000000000000011110011101101111101100110000 #
b0000000000000000000000000000000000011111000111010110111010001100 '
b01100000111101010000000100001101 (
#281
b0001111001110110111110111101010110010010011111101110000011011110 !
1&
b0001111001110110111110111101010110010010011111101110000011011110 $
#286
b11100000111100000000000000101100 %
b0000000000000000000000000000000000000000000000000010110011011100 "
0&
b0000000000000000000000000000000000000000000010001100100101100000 #
b0000000000000000000000000000000000000000111011100100110010100100 '
b00000000000010100000000100000101 (
#291
b0000000000001000110010100100010101010110011010000010110011011100 !
1&
b0000000000001000110010100100010101010110011010000010110011011100 $
#296
b11100000111100000000000001100101 %
b0000000000000000000000000000000000000000000001000101100101011110 "
0&
b0000000000000000000000000000000001110001010100010000011110010000 #
b0000000000000000000000000000000001111011001101111101100000000001 '
b10000000111101110000101100000110 (
#301
b0111000101010001000100010111001001110111000101110101100101011110 !
1&
b0111000101010001000100010111001001110111000101110101100101011110 $
#306
b00110000111100000000000011100001 %
b0000000000000000000000000000000000000000000001100010110100100111 "
0&
b0000000000000000000000000000000000001001010011010001110110000000 #
b0000000000000000000000000000000000001010110101011111010011011111 '
b00110000101010000000011100000111 (
#311
b0000100101001101000111110000001010101010001111100010110100100111 !
1&
b0000100101001101000111110000001010101010001111100010110100100111 $
#316
b10000000110100000000000010011001 %
b0000000000000000000000000000000000000000000001110011001010010011 "
0&
b0000000000000000000000000000000001111001001001101010000011100000 #
b0000000000000000000000000000000001111111110011010000001010111001 '
b11110000110001100000110000001011 (
#321
b0111100100100110101001110111111100101111010011010011001010010011 !
1&
b0111100100100110101001110111111100101111010011010011001010010011 $
#326
b00110000110000000000000000010010 %
b0000000000000000000000000000000000000000000000001001000001001000 "
0&
b0000000000000000000000000000000000001111010001001100001010000000 #
b0000000000000000000000000000000000010000110100011011100100000100 '
b01010000001011100000100000000100 (
#331
b0000111101000100110001000000110001100110001111001001000001001000 !
1&
b0000111101000100110001000000110001100110001111001001000001001000 $
#336
b11010000101000000000000000000001 %
b0000000000000000000000000000000000000000000000000000011000001100 "
0&
b0000000000000000000000000000000010101001110010110101100001000000 #
b0000000000000000000000000000000010101110101110011011011000100110 '
b11010000010110100000011000001100 (
#341
b1010100111001011010111010010111001010111110110100000011000001100 !
1&
b1010100111001011010111010010111001010111110110100000011000001100 $
#346
b11100000111100000000000000010010 %
b0000000000000000000000000000000000000000000000000100100001111110 "
0&
b0000000000000000000000000000000010110111010111110110011011100000 #
b0000000000000000000000000000000010111010111110000100001001110010 '
b11010000101100100000010000000111 (
#351
b1011011101011111011010100111100010010011000101000100100001111110 !
1&
b1011011101011111011010100111100010010011000101000100100001111110 $
#356
b01010000000100000000000011000110 %
b0000000000000000000000000000000000000000000000011001010010000010 "
0&
b0000000000000000000000000000000000100011000110110000010000000000 #
b0000000000000000000000000000000000100100000101101111101010110010 '
b01110000010000000000001000001011 (
#361
b0010001100011011000001001111101001100010001100011001010010000010 !
1&
b0010001100011011000001001111101001100010001100011001010010000010 $
#366
b00000000010100000000000001101011 %
b0000000000000000000000000000000000000000000001001001110011000011 "
0&
b0000000000000000000000000000000000000000000011110011010010000000 #
b0000000000000000000000000000000000000000001010111001101001001011 '
b00110000101010000000101100001001 (
#371
b0000000000001111001101001001011111001001000011001001110011000011 !
1&
b0000000000001111001101001001011111001001000011001001110011000011 $
#376
b11100000001000000000000000101101 %
b0000000000000000000000000000000000000000000000101010010000111011 "
0&
b0000000000000000000000000000000000000000110110011111111100100000 #
b0000000000000000000000000000000000001110000001001101000000000000 '
b00000000111110010000111100000111 (
#381
b0000000011011010000011000100100000101100101001111010010000111011 !
1&
b0000000011011010000011000100100000101100101001111010010000111011 $
#386
b00110000111100000000000011101100 %
b0000000000000000000000000000000000000000000000000000000111011000 "
0&
b0000000000000000000000000000000000101101111111100111000001100000 #
b0000000000000000000000000000000000101110110111001010001000010000 '
b11110000100110100000000000000010 (
#391
b0010110111111110011100010011111000101111110110000000000111011000 !
1&
b0010110111111110011100010011111000101111110110000000000111011000 $
#396
b00100000000100000000000000100101 %
b0000000000000000000000000000000000000000000000000010011011100001 "
0&
b0000000000000000000000000000000000010100000010101110000001110000 #
b0000000000000000000000000000000000010100010000111101100100100100 '
b10100000000001110000000100001101 (
#401
b0001010000001010111000001010100011010001110100110010011011100001 !
1&
b0001010000001010111000001010100011010001110100110010011011100001 $
#406
b11110000000100000000000010011001 %
b0000000000000000000000000000000000000000000001110011000111111010 "
0&
b0000000000000000000000000000000010110100011110111001011101110000 #
b0000000000000000000000000000000011000000001111111111000100101001 '
b11000000011101110000110000001010 (
#411
b1011010001111011101000110010110100100111110001100011000111111010 !
1&
b1011010001111011101000110010110100100111110001100011000111111010 $
#416
b01110000101000000000000001111001 %
b0000000000000000000000000000000000000000000000111100110100110011 "
0&
b0000000000000000000000000000000001011011110110001010101100100000 #
b0000000000000000000000000000000001011111110010001111110001010000 '
b11010000110001010000100000001011 (
#421
b0101101111011000101011110000110010000100000000001100110100110011 !
1&
b0101101111011000101011110000110010000100000000001100110100110011 $
#426
b00000000100000000000000010000001 %
b0000000000000000000000000000000000000000000000011000011110001001 "
0&
b0000000000000000000000000000000000000000011110000100010100000000 #
b0000000000000000000000000000000000000000111101001000011010010011 '
b11110000100010100000001100001001 (
#431
b0000000001111000010001010111101010111010000010111000011110001001 !
1&
b0000000001111000010001010111101010111010000010111000011110001001 $
#436
b01010000101100000000000001100000 %
b0000000000000000000000000000000000000000000001001000001100000000 "
0&
b0000000000000000000000000000000000001010001000111000110110010000 #
b0000000000000000000000000000000000001101111111101110011000110000 '
b00100000001010110000110000001000 (
#441
b0000101000100011100100010110011011010101101001001000001100000000 !
1&
b0000101000100011100100010110011011010101101001001000001100000000 $
#446
b01110000101000000000000010001101 %
b0000000000000000000000000000000000000000000000101100000110001101 "
0&
b0000000000000000000000000000000001010100101110111100000001000000 #
b0000000000000000000000000000000001010111010111000010011100111111 '
b11000000100110100000010100000001 (
#451
b0101010010111011110000101101110110100101011101001100000110001101 !
1&
b0101010010111011110000101101110110100101011101001100000110001101 $
#456
b01000000111100000000000010000011 %
b0000000000000000000000000000000000000000000000110001001000000000 "
0&
b0000000000000000000000000000000000101000101101111111110110100000 #
b0000000000000000000000000000000000101010100100101101010000110010 '
b10100000100001100000011000000000 (
#461
b0010100010110111111111110111011111000100100101010001001000000000 !
1&
b0010100010110111111111110111011111000100100101010001001000000000 $
#466
b00100000010000000000000010111100 %
b0000000000000000000000000000000000000000000010000001101101011000 "
0&
b0000000000000000000000000000000000001110001100010100101001000000 #
b0000000000000000000000000000000000001111111100000010010000110100 '
b01110000101010010000101100001010 (
#471
b0000111000110001010010111111011010111110101001000001101101011000 !
1&
b0000111000110001010010111111011010111110101001000001101101011000 $
#476
b11000000011100000000000010110001 %
b0000000000000000000000000000000000000000000010011010111101100010 "
0&
b0000000000000000000000000000000001101100111111000110111001000000 #
b0000000000000000000000000000000001110111111100011111110010111110 '
b10010000111111000000111000000010 (
#481
b0110110011111100011110010010101111011111001001011010111101100010 !
1&
b0110110011111100011110010010101111011111001001011010111101100010 $
#486
b00000000110000000000000001101100 %
b0000000000000000000000000000000000000000000001010111110110110000 "
0&
b0000000000000000000000000000000000000000101010000010010110000000 #
b0000000000000000000000000000000000000001000101011111101101001000 '
b11100000001100100000110100000100 (
#491
b0000000010101000001001011110100001011000000111010111110110110000 !
1&
b0000000010101000001001011110100001011000000111010111110110110000 $
#496
b00010000101100000000000011010010 %
b0000000000000000000000000000000000000000000001110110001011010010 "
0&
b0000000000000000000000000000000000000101001111000110100100010000 #
b0000000000000000000000000000000000000110000110111111000010101000 '
b01010000010100110000100100000001 (
#501
b0000010100111100011010011110100000100100110011010110001011010010 !
1&
b0000010100111100011010011110100000100100110011010110001011010010 $
#506
b00100000100000000000000010100010 %
b0000000000000000000000000000000000000000000001101111110001010100 "
0&
b0000000000000000000000000000000000011100100100000011111100000000 #
b0000000000000000000000000000000000011110100011000110000100010000 '
b11100000111111100000101100001010 (
#511
b0001110010010000010000001111010100100101110000101111110001010100 !
1&
b0001110010010000010000001111010100100101110000101111110001010100 $
#516
b01100000001000000000000011011101 %
b0000000000000000000000000000000000000000000000110111110101111111 "
0&
b0000000000000000000000000000000000000000010101101011110011100000 #
b0000000000000000000000000000000000000001110111111010001100101010 '
b00000000111001110000010000001011 (
#521
b0000000001010110101111100110010101101000110011100111110101111111 !
1&
b0000000001010110101111100110010101101000110011100111110101111111 $
#526
b10010000111000000000000001101111 %
b0000000000000000000000000000000000000000000001100001010000101011 "
0&
b0000000000000000000000000000000001111111010000101100010000000000 #
b0000000000000000000000000000000010000111100110010110110110101011 '
b11100000111000000000111000000101 (
#531
b0111111101000010110011000101000010010101100001100001010000101011 !
1&
b0111111101000010110011000101000010010101100001100001010000101011 $
#536
b10110000001000000000000011100010 %
b0000000000000000000000000000000000000000000001010101000101001100 "
0&
b0000000000000000000000000000000001000010010111000111111010100000 #
b0000000000000000000000000000000001000110110110111101011111110110 '
b01100000011101010000011000000110 (
#541
b0100001001011100100000110001101000001000000011110101000101001100 !
1&
b0100001001011100100000110001101000001000000011110101000101001100 $
#546
b11100000111100000000000011011011 %
b0000000000000000000000000000000000000000000010010110110001101100 "
0&
b0000000000000000000000000000000001111111010100101101100110000000 #
b0000000000000000000000000000000010001001100001100001000000100100 '
b10010000111010000000101100000100 (
#551
b0111111101010010111000111010100111001010010000010110110001101100 !
1&
b0111111101010010111000111010100111001010010000010110110001101100 $
#556
b00000000100100000000000001100000 %
b0000000000000000000000000000000000000000000000000110001101100000 "
0&
b0000000000000000000000000000000000000000000010010101010110000000 #
b0000000000000000000000000000000000000000000100001000011011110000 '
b00010000100110000000000100001001 (
#561
b0000000000001001010101011000011011001110000100000110001101100000 !
1&
b0000000000001001010101011000011011001110000100000110001101100000 $
#566
b11010000110000000000000000001010 %
b0000000000000000000000000000000000000000000000000101000001101110 "
0&
b0000000000000000000000000000000010101001111111010000100101000000 #
b0000000000000000000000000000000010110000100101000111011010010100 '
b11010000011101110000100000001011 (
#571
b1010100111111101000011111101011100011100111001100101000001101110 !
1&
b1010100111111101000011111101011100011100111001100101000001101110 $
#576
b11110000100000000000000001111111 %
b0000000000000000000000000000000000000000000001101111100101110001 "
0&
b0000000000000000000000000000000000101101010101101111000110000000 #
b0000000000000000000000000000000000111010101010101111001110101110 '
b00110000010000110000111000001111 (
#581
b0010110101010110111111101100110100001000110000111111100101110001 !
1&
b0010110101010110111111101100110100001000110000111111100101110001 $
#586
b11100000011100000000000001110001 %
b0000000000000000000000000000000000000000000000110001011111100010 "
0&
b0000000000000000000000000000000010011010011111101111100011110000 #
b0000000000000000000000000000000010100000111101001010101011011011 '
b10110000001110010000011100000010 (
#591
b1001101001111110111111110110001010011010000011000001011111100010 !
1&
b1001101001111110111111110110001010011010000011000001011111100010 $
#596
b01010000110100000000000011101001 %
b0000000000000000000000000000000000000000000000001111001100000011 "
0&
b0000000000000000000000000000000000110010100100000011010010010000 #
b0000000000000000000000000000000000110011011101110011100101111000 '
b10100000001011010000000100001011 (
#601
b0011001010010000001101010111011000010001111001011111001100000011 !
1&
b0011001010010000001101010111011000010001111001011111001100000011 $
#606
b11000000011000000000000001010000 %
b0000000000000000000000000000000000000000000000100011000000000000 "
0&
b0000000000000000000000000000000000001100001110110101101010100000 #
b0000000000000000000000000000000000010001100001010100000011010000 '
b00010000010001110000011100000000 (
#611
b0000110000111011010111111110011110110110001100100011000000000000 !
1&
b0000110000111011010111111110011110110110001100100011000000000000 $
#616
b00110000001100000000000001010110 %
b0000000000000000000000000000000000000000000000100101101010101100 "
0&
b0000000000000000000000000000000000010010001001100010010000010000 #
b0000000000000000000000000000000000010011100110101001001100001110 '
b01100000011010110000011100000010 (
#621
b0001001000100110001001011000001000010100010101000101101010101100 !
1&
b0001001000100110001001011000001000010100010101000101101010101100 $
#626
b00000000110000000000000011010110 %
b0000000000000000000000000000000000000000000000011011010001011100 "
0&
b0000000000000000000000000000000000000000000000000110011011000000 #
b0000000000000000000000000000000000000000000001000001010100100010 '
b00000000100010010000001000001010 (
#631
b0000000000000000011001101100000111111010000001111011010001011100 !
1&
b0000000000000000011001101100000111111010000001111011010001011100 $
#636
b10010000001100000000000000001000 %
b0000000000000000000000000000000000000000000000000010000000110000 "
0&
b0000000000000000000000000000000001010001100111001000101100100000 #
b0000000000000000000000000000000001010011111001010101001110100000 '
b10010000111001100000010000000110 (
#641
b0101000110011100100011010110100010101000010100000010000000110000 !
1&
b0101000110011100100011010110100010101000010100000010000000110000 $
#646
b00110000001100000000000010010101 %
b0000000000000000000000000000000000000000000000001001110010010001 "
0&
b0000000000000000000000000000000000011011001100000100010100110000 #
b0000000000000000000000000000000000011011101101111001010111110110 '
b10010000011100010000000100001101 (
#651
b0001101100110000010001011011011010110100001101011001110010010001 !
1&
b0001101100110000010001011011011010110100001101011001110010010001 $
#656
b10000000100100000000000011001000 %
b0000000000000000000000000000000000000000000000000000010101111000 "
0&
b0000000000000000000000000000000001000000100001100100010111000000 #
b0000000000000000000000000000000001000000111011100011000000001000 '
b10000000011111000000000000000111 (
#661
b0100000010000110010001100010011111100100110100000000010101111000 !
1&
b0100000010000110010001100010011111100100110100000000010101111000 $
#666
b11000000011000000000000000101011 %
b0000000000000000000000000000000000000000000000010010111011011001 "
0&
b0000000000000000000000000000000000111100110000101001001000100000 #
b0000000000000000000000000000000001000010000111000011100111100010 '
b01010000110110110000011100001011 (
#671
b0011110011000010100101110111100001111000111010100010111011011001 !
1&
b0011110011000010100101110111100001111000111010100010111011011001 $
#676
b11010000100000000000000000100101 %
b0000000000000000000000000000000000000000000000010000001110010100 "
0&
b0000000000000000000000000000000000110100001101000101110010000000 #
b0000000000000000000000000000000000111001111101010110010110110001 '
b01000000000110010000011100000100 (
#681
b0011010000110100011000100100000000000101100111100000001110010100 !
1&
b0011010000110100011000100100000000000101100111100000001110010100 $
#686
b01110000001100000000000001010100 %
b0000000000000000000000000000000000000000000000001111110101010000 "
0&
b0000000000000000000000000000000001010100010010001100111111000000 #
b0000000000000000000000000000000001010101110110110011100101100000 '
b11000000010101000000001100000100 (
#691
b0101010001001000110100010101000101101100010100001111110101010000 !
1&
b0101010001001000110100010101000101101100010100001111110101010000 $
#696
b10110000000000000000000000000001 %
b0000000000000000000000000000000000000000000000000000010000000011 "
0&
b0000000000000000000000000000000010001111001110100111000000000000 #
b0000000000000000000000000000000010010001111111010101010001011000 '
b11010000010101010000010000000011 (
#701
b1000111100111010011100101100001011100000010101010000010000000011 !
1&
b1000111100111010011100101100001011100000010101010000010000000011 $
#706
b10110000111100000000000010111111 %
b0000000000000000000000000000000000000000000000100100001011111000 "
0&
b0000000000000000000000000000000001011000011110100001001011010000 #
b0000000000000000000000000000000001011010111101000010111110000101 '
b10000000000000110000001100001000 (
#711
b0101100001111010000101010100011111011001101111110100001011111000 !
1&
b0101100001111010000101010100011111011001101111110100001011111000 $
#716
b10100000101000000000000010110100 %
b0000000000000000000000000000000000000000000000001011111010001100 "
0&
b0000000000000000000000000000000001010000110110100000100110000000 #
b0000000000000000000000000000000001010001110111110110110000011100 '
b10000000110111000000000100001111 (
#721
b0101000011011010000010101000010010100100000100001011111010001100 !
1&
b0101000011011010000010101000010010100100000100001011111010001100 $
#726
b00000000110000000000000001010011 %
b0000000000000000000000000000000000000000000000100100100011100100 "
0&
b0000000000000000000000000000000000000000001100000100101111000000 #
b0000000000000000000000000000000000000000010011001011111001100011 '
b01000000011001010000011100001100 (
#731
b0000000000110000010010111101101000101001110000010100100011100100 !
1&
b0000000000110000010010111101101000101001110000010100100011100100 $
#736
b01000000100100000000000001001001 %
b0000000000000000000000000000000000000000000000000000000010010010 "
0&
b0000000000000000000000000000000000010000010111011100000011010000 #
b0000000000000000000000000000000000010000011100001100001111001111 '
b01000000111001010000000000000010 (
#741
b0001000001011101110000001110001100000010011011010000000010010010 !
1&
b0001000001011101110000001110001100000010011011010000000010010010 $
#746
b11100000010100000000000011010101 %
b0000000000000000000000000000000000000000000000110101011101010100 "
0&
b0000000000000000000000000000000010011011000001011100100111000000 #
b0000000000000000000000000000000010011111001000010001011010110000 '
b10110000111011000000010000000100 (
#751
b1001101100000101110011011101011111110101100111110101011101010100 !
1&
b1001101100000101110011011101011111110101100111110101011101010100 $
